QGCN/__init__.py
QGCN/activator.py
QGCN/params.py
QGCN/QGCN_model/QGCN.py
QGCN/QGCN_model/__init__.py
QGCN/QGCN_model/qgcn_activator.py
QGCN/dataset/__init__.py
QGCN/dataset/dataset_external_data.py
QGCN/dataset/dataset_graphs_model.py
QGCN/graphs_package/__init__.py
QGCN/graphs_package/README_how_to_use/README_HOW_TO_USE.py
QGCN/graphs_package/README_how_to_use/__init__.py
QGCN/graphs_package/features_processor/__init__.py
QGCN/graphs_package/features_processor/features_processor.py
QGCN/graphs_package/features_processor/motif_ratio.py
QGCN/graphs_package/features_processor/motif_variations/__init__.py
QGCN/graphs_package/features_processor/motif_variations/isomorphic.py
QGCN/graphs_package/multi_graph/__init__.py
QGCN/graphs_package/multi_graph/multi_graph.py
QGCN/graphs_package/temporal_graphs/__init__.py
QGCN/graphs_package/temporal_graphs/temporal_graph.py
QGCN/graphs_package/temporal_graphs/temporal_multi_graph.py
QGCN-0.0.17.dist-info/LICENSE
QGCN-0.0.17.dist-info/METADATA
QGCN-0.0.17.dist-info/WHEEL
QGCN-0.0.17.dist-info/top_level.txt
QGCN-0.0.17.dist-info/RECORD
