Metadata-Version: 2.1
Name: QGCN
Version: 0.0.17
Summary: a qgcn model package
Author: YOLO LAB
Classifier: Programming Language :: Python :: 3
Classifier: License :: OSI Approved :: MIT License
Classifier: Operating System :: OS Independent
Requires-Python: >=3.6
License-File: LICENSE
Requires-Dist: scipy
Requires-Dist: pandas
Requires-Dist: numpy
Requires-Dist: torch
Requires-Dist: scikit-learn
Requires-Dist: bokeh
Requires-Dist: matplotlib
Requires-Dist: bitstring
Requires-Dist: python-louvain
Requires-Dist: graph-measures (>=0.1.44)
